{
  "Tooltip_modifier_type": "Тип",
  "Tooltip_modifier_standard": "Стандартный",
  "Tooltip_modifier_damage": "урон",
  "Tooltip_modifier_attack_speed": "скорость атаки",
  "Tooltip_modifier_knockback": "отталкивание",
  "Tooltip_modifier_minrange": "минимальная дальность",
  "Tooltip_modifier_maxrange": "максимальная дальность",
  "Tooltip_modifier_crit": "шанс крит. удара",
  "Tooltip_modifier_durability": "прочность",
  "Tooltip_modifier_endurance_cost": "расход выносливости",
  "Tooltip_modifier_accuracy": "точность",
  "Tooltip_modifier_recoil": "разброс",
  "Tooltip_modifier_aim_time": "время прицеливания",
  "Tooltip_modifier_reload_time": "время перезарядки",
  "Tooltip_modifier_noise": "громкость",
  "Tooltip_modifier_experience": "опыт",
  "Tooltip_modifier_capacity": "ёмкость",
  "Tooltip_modifier_weight_reduction": "снижение веса",
  "Tooltip_modifier_weight": "вес",
  "Tooltip_modifier_container_weight": "веса контейнера",
  "Tooltip_modifier_container_capacity": "ёмкости контейнера",
  "Tooltip_modifier_footwear_noise": "громкость шагов",
  "Tooltip_modifier_run_speed": "скорость бега",
  "Tooltip_modifier_scratch_defense": "защита от царапин",
  "Tooltip_modifier_bite_defense": "защита от укусов",
  "Tooltip_modifier_bullet_defense": "защита от пуль",
  "Tooltip_modifier_combat_speed": "скорость боя",
  "Tooltip_modifier_jam_chance": "шанс клина",
  "Tooltip_modifier_light": "яркость света",
  "Tooltip_modifier_battery": "расход батареи",
  "Tooltip_item_stats_damage": "Урон",
  "Tooltip_item_stats_crit": "Крит. урон",
  "Tooltip_item_stats_range": "Дальность",
  "Tooltip_item_stats_break_chance": "Шанс поломки",
  "Tooltip_item_stats_break_chance_one_in": "1 из",
  "Tooltip_item_stats_recoil_aim_reload": "Разброс/Прицеливание/Перезарядка",
  "Tooltip_item_stats_sound_radius": "Радиус слышимости",
  "Tooltip_item_stats_accuracy": "Точность",
  "Tooltip_item_stats_knockback": "Отталкивание",
  "Tooltip_item_stats_attack_speed": "Скорость атаки",
  "Tooltip_item_stats_endurance_used": "Использование выносливости",
  "Tooltip_item_stats_tiles": "метров",
  "Tooltip_BookTitle_Tinkering": "Эта книга содержит сведения об инженерии.",
  "Tooltip_TinkeringMag": "Вводное руководство по искусству перековки.<br>Раскрывает базовые концепции и техники, необходимые для начала модификации снаряжения.",
  "Tooltip_modifier_xp_bonus": "XP",
  "Tooltip_modifier_max_ammo": "ёмкость магазина",
  "Tooltip_modifier_reading_speed": "скорость чтения"
}