<?xml version="1.0" encoding="utf-8"?>
<clothingItem>
	<m_GUID>7d474b8b-2b20-40fa-8b0a-fb843030ff32</m_GUID>
	<m_MaleModel>skinned\backpacks\m_alice_pack_fat</m_MaleModel>
	<m_FemaleModel>skinned\backpacks\f_alice_pack_fat</m_FemaleModel>
	<m_AltMaleModel></m_AltMaleModel>
	<m_AltFemaleModel></m_AltFemaleModel>
	<m_Static>false</m_Static>
	<m_AllowRandomHue>false</m_AllowRandomHue>
	<m_AllowRandomTint>false</m_AllowRandomTint>
	<m_AttachBone></m_AttachBone>
	<textureChoices>clothes\bag\alicepack_desert</textureChoices>
</clothingItem>