<?xml version="1.0" encoding="utf-8"?>
<clothingItem>
	<m_MaleModel>skinned\clothes\Logs3StackRight</m_MaleModel>
	<m_FemaleModel>skinned\clothes\Logs3StackRight</m_FemaleModel>
	<m_GUID>15ad4210-2264-451a-a018-a15522fcfc24</m_GUID>
	<m_Static>false</m_Static>
	<m_AllowRandomHue>false</m_AllowRandomHue>
	<m_AllowRandomTint>false</m_AllowRandomTint>
	<m_AttachBone></m_AttachBone>
	<m_MasksFolder>media/textures/Clothes/Hat/Masks</m_MasksFolder>
	<textureChoices>WorldItems\Log</textureChoices>
	
</clothingItem>