{
    "Base.WhodunitCards": "Whodunit Deck",
    "Base.WhodunitBoard": "Whodunit Board",
    "Base.Whodunit_Box": "Whodunit Box",
    "Base.WhodunitPlum": "Mr. Plum (Whodunit)",
    "Base.WhodunitWhite": "Mrs. White (Whodunit)",
    "Base.WhodunitScarlet": "Ms. Scarlet (Whodunit)",
    "Base.WhodunitPeacock": "Mr. Peacock (Whodunit)",
    "Base.WhodunitGreen": "Mr. Green (Whodunit)",
    "Base.WhodunitMustard": "Col. Mustard (Whodunit)",
    "Base.WhodunitCandlestick": "Candlestick (Whodunit)",
    "Base.WhodunitKnife": "Knife (Whodunit)",
    "Base.WhodunitRope": "Rope (Whodunit)",
    "Base.WhodunitPistol": "Pistol (Whodunit)",
    "Base.WhodunitWrench": "Wrench (Whodunit)",
    "Base.WhodunitLeadpipe": "Leadpipe (Whodunit)"
}